{
    "name": "Python Web Scraping",
    "dockerComposeFile": ["../docker-compose.yml"],
    "service": "app",
    "workspaceFolder": "/workspace",
    "customizations": {
        "vscode": {
            "settings": {
                "python.defaultInterpreterPath": "/usr/local/bin/python",
                "python.linting.enabled": true,
                "python.linting.pylintEnabled": true,
                "python.formatting.provider": "black",
                "python.formatting.blackPath": "/usr/local/bin/black",
                "editor.formatOnSave": true,
                "editor.rulers": [88],
                "python.testing.pytestEnabled": true
            },
            "extensions": [
                "ms-python.python",
                "ms-python.vscode-pylance",
                "njpwerner.autodocstring"
            ]
        }
    },
    "remoteUser": "vscode"
}